xlavir/__about__.py
xlavir/__init__.py
xlavir/cli.py
xlavir/images.py
xlavir/util.py
xlavir/xlavir.py
xlavir/io/__init__.py
xlavir/io/ct.py
xlavir/io/excel_sheet_dataframe.py
xlavir/io/xl.py
xlavir/qc/__init__.py
xlavir/qc/quality_requirements.py
xlavir/tools/__init__.py
xlavir/tools/consensus.py
xlavir/tools/fastp.py
xlavir/tools/mosdepth.py
xlavir/tools/nextclade.py
xlavir/tools/pangolin.py
xlavir/tools/samtools.py
xlavir/tools/variants.py
xlavir/tools/nextflow/__init__.py
xlavir/tools/nextflow/exec_report.py
xlavir-1.0.2.dist-info/METADATA
xlavir-1.0.2.dist-info/WHEEL
xlavir-1.0.2.dist-info/entry_points.txt
xlavir-1.0.2.dist-info/licenses/LICENSE
xlavir-1.0.2.dist-info/RECORD
