Metadata-Version: 2.1
Name: xlavir
Version: 1.0.2
Summary: Excel report from viral sequencing analysis output
Project-URL: Homepage, https://github.com/CFIA-NCFAD/xlavir
Project-URL: Repository, https://github.com/CFIA-NCFAD/xlavir.git
Project-URL: Bug Tracker, https://github.com/CFIA-NCFAD/xlavir/issues
Author-email: Peter Kruczkiewicz <peter.kruczkiewicz@gmail.com>
License: MIT License
License-File: LICENSE
Keywords: bioinformatics,excel report,nextflow,virus sequencing
Classifier: Development Status :: 5 - Production/Stable
Classifier: Environment :: Console
Classifier: Intended Audience :: Science/Research
Classifier: License :: OSI Approved :: MIT License
Classifier: Natural Language :: English
Classifier: Operating System :: POSIX :: Linux
Classifier: Programming Language :: Python :: 3
Classifier: Programming Language :: Python :: 3 :: Only
Classifier: Programming Language :: Python :: 3.8
Classifier: Programming Language :: Python :: 3.9
Classifier: Programming Language :: Python :: 3.10
Classifier: Programming Language :: Python :: 3.11
Classifier: Programming Language :: Unix Shell
Classifier: Topic :: Scientific/Engineering :: Bio-Informatics
Classifier: Topic :: Utilities
Requires-Python: >=3.8
Requires-Dist: beautifulsoup4
Requires-Dist: biopython
Requires-Dist: imageio
Requires-Dist: numpy>=1.20.0
Requires-Dist: odfpy
Requires-Dist: openpyxl
Requires-Dist: pandas
Requires-Dist: pydantic
Requires-Dist: pysam
Requires-Dist: rich
Requires-Dist: typer
Requires-Dist: xlsxwriter
Provides-Extra: dev
Requires-Dist: mypy; extra == 'dev'
Requires-Dist: ruff; extra == 'dev'
Requires-Dist: twine; extra == 'dev'
Requires-Dist: wheel; extra == 'dev'
Provides-Extra: test
Requires-Dist: pytest-runner; extra == 'test'
Requires-Dist: pytest>=3; extra == 'test'
